mlpf/__init__.py
mlpf/data/__init__.py
mlpf/data/analysis/__init__.py
mlpf/data/analysis/utils.py
mlpf/data/analysis/description/__init__.py
mlpf/data/analysis/description/describe.py
mlpf/data/analysis/description/describe_grid.py
mlpf/data/analysis/description/describe_node.py
mlpf/data/analysis/visualization/__init__.py
mlpf/data/analysis/visualization/grid_pdf_estimates.py
mlpf/data/analysis/visualization/node_pdf_estimates.py
mlpf/data/analysis/visualization/visualize.py
mlpf/data/conversion/__init__.py
mlpf/data/conversion/utils.py
mlpf/data/conversion/numpy/__init__.py
mlpf/data/conversion/numpy/optimal_power_flow.py
mlpf/data/conversion/numpy/power_flow.py
mlpf/data/conversion/torch/__init__.py
mlpf/data/conversion/torch/optimal_power_flow.py
mlpf/data/conversion/torch/power_flow.py
mlpf/data/data/__init__.py
mlpf/data/data/optimal_power_flow.py
mlpf/data/data/power_flow.py
mlpf/data/generate/__init__.py
mlpf/data/generate/generate_uniform_data.py
mlpf/data/loading/__init__.py
mlpf/data/loading/load_data.py
mlpf/data/masks/__init__.py
mlpf/data/masks/optimal_power_flow.py
mlpf/data/masks/power_flow.py
mlpf/data/utils/__init__.py
mlpf/data/utils/pandapower_networks.py
mlpf/data/utils/saving.py
mlpf/enumerations/__init__.py
mlpf/enumerations/branch_table.py
mlpf/enumerations/bus_table.py
mlpf/enumerations/bus_type.py
mlpf/enumerations/gencost_table.py
mlpf/enumerations/generator_table.py
mlpf/enumerations/power_flow_ids.py
mlpf/enumerations/ppc_tables.py
mlpf/loss/__init__.py
mlpf/loss/relative_values.py
mlpf/loss/numpy/__init__.py
mlpf/loss/numpy/bound_errors.py
mlpf/loss/numpy/costs.py
mlpf/loss/numpy/power_flow.py
mlpf/loss/numpy/utils.py
mlpf/loss/numpy/metrics/__init__.py
mlpf/loss/numpy/metrics/active.py
mlpf/loss/numpy/metrics/costs.py
mlpf/loss/numpy/metrics/metrics.py
mlpf/loss/numpy/metrics/reactive.py
mlpf/loss/numpy/metrics/utils.py
mlpf/loss/numpy/metrics/bounds/__init__.py
mlpf/loss/numpy/metrics/bounds/active.py
mlpf-0.0.9.dist-info/LICENCE.txt
mlpf-0.0.9.dist-info/METADATA
mlpf-0.0.9.dist-info/WHEEL
mlpf-0.0.9.dist-info/top_level.txt
mlpf-0.0.9.dist-info/RECORD
