Metadata-Version: 2.1
Name: mlpf
Version: 0.0.9
Summary: Machine learning for power flow
Home-page: 
Author: Viktor Todosijevic
Author-email: todosijevicviktor998@gmail.com
License: MIT
Keywords: machine learning,power flow
Classifier: Development Status :: 3 - Alpha
Classifier: Intended Audience :: Science/Research
Classifier: Operating System :: OS Independent
Classifier: License :: OSI Approved :: MIT License
Classifier: Programming Language :: Python :: 3
Classifier: Topic :: Scientific/Engineering :: Artificial Intelligence
License-File: LICENCE.txt
Requires-Dist: numpy
Requires-Dist: pandapower
Requires-Dist: PYPOWER
Requires-Dist: scikit-learn
Requires-Dist: scipy
Requires-Dist: tqdm
